model_suite/__init__.py
model_suite/base_config.py
model_suite/base_model.py
model_suite/models/__init__.py
model_suite/models/ae/__init__.py
model_suite/models/ae/model_architecture.py
model_suite/models/ae/model_config.py
model_suite/models/alexnet/__init__.py
model_suite/models/alexnet/model_architecture.py
model_suite/models/alexnet/model_config.py
model_suite/models/mlp/__init__.py
model_suite/models/mlp/model_architecture.py
model_suite/models/mlp/model_config.py
model_suite/models/resnet/__init__.py
model_suite/models/resnet/model_architecture.py
model_suite/models/resnet/model_config.py
model_suite/models/unet/__init__.py
model_suite/models/unet/model_architecture.py
model_suite/models/unet/model_config.py
model_suite/models/vgg/__init__.py
model_suite/models/vgg/model_architecture.py
model_suite/models/vgg/model_config.py
model_suite/models/vit/__init__.py
model_suite/models/vit/model_architecture.py
model_suite/models/vit/model_config.py
model_suite-0.0.5.dist-info/LICENSE
model_suite-0.0.5.dist-info/METADATA
model_suite-0.0.5.dist-info/WHEEL
model_suite-0.0.5.dist-info/top_level.txt
model_suite-0.0.5.dist-info/RECORD
